libnmstate/VERSION
libnmstate/__init__.py
libnmstate/dns.py
libnmstate/error.py
libnmstate/iplib.py
libnmstate/net_state.py
libnmstate/netapplier.py
libnmstate/netinfo.py
libnmstate/nmstate.py
libnmstate/plugin.py
libnmstate/prettystate.py
libnmstate/route.py
libnmstate/route_rule.py
libnmstate/schema.py
libnmstate/state.py
libnmstate/validator.py
libnmstate/version.py
libnmstate/ifaces/__init__.py
libnmstate/ifaces/base_iface.py
libnmstate/ifaces/bond.py
libnmstate/ifaces/bridge.py
libnmstate/ifaces/dummy.py
libnmstate/ifaces/ethernet.py
libnmstate/ifaces/ethtool.py
libnmstate/ifaces/ifaces.py
libnmstate/ifaces/infiniband.py
libnmstate/ifaces/linux_bridge.py
libnmstate/ifaces/linux_bridge_port_vlan.py
libnmstate/ifaces/macvlan.py
libnmstate/ifaces/macvtap.py
libnmstate/ifaces/ovs.py
libnmstate/ifaces/veth.py
libnmstate/ifaces/vlan.py
libnmstate/ifaces/vrf.py
libnmstate/ifaces/vxlan.py
libnmstate/nispor/__init__.py
libnmstate/nispor/base_iface.py
libnmstate/nispor/bond.py
libnmstate/nispor/bridge.py
libnmstate/nispor/bridge_port_vlan.py
libnmstate/nispor/dummy.py
libnmstate/nispor/ethernet.py
libnmstate/nispor/macvlan.py
libnmstate/nispor/macvtap.py
libnmstate/nispor/ovs.py
libnmstate/nispor/plugin.py
libnmstate/nispor/route.py
libnmstate/nispor/route_rule.py
libnmstate/nispor/veth.py
libnmstate/nispor/vlan.py
libnmstate/nispor/vrf.py
libnmstate/nispor/vxlan.py
libnmstate/nm/__init__.py
libnmstate/nm/active_connection.py
libnmstate/nm/bond.py
libnmstate/nm/bridge.py
libnmstate/nm/bridge_port_vlan.py
libnmstate/nm/checkpoint.py
libnmstate/nm/common.py
libnmstate/nm/connection.py
libnmstate/nm/context.py
libnmstate/nm/device.py
libnmstate/nm/dns.py
libnmstate/nm/ethtool.py
libnmstate/nm/ieee_802_1x.py
libnmstate/nm/infiniband.py
libnmstate/nm/ipv4.py
libnmstate/nm/ipv6.py
libnmstate/nm/lldp.py
libnmstate/nm/macvlan.py
libnmstate/nm/ovs.py
libnmstate/nm/plugin.py
libnmstate/nm/profile.py
libnmstate/nm/profiles.py
libnmstate/nm/route.py
libnmstate/nm/sriov.py
nmstate-2.0.0.dist-info/LICENSE
nmstate-2.0.0.dist-info/METADATA
nmstate-2.0.0.dist-info/WHEEL
nmstate-2.0.0.dist-info/entry_points.txt
nmstate-2.0.0.dist-info/top_level.txt
nmstate-2.0.0.dist-info/RECORD
