Metadata-Version: 2.1
Name: nmstate
Version: 2.0.0
Summary: Declarative network manager API
Home-page: https://nmstate.github.io/
Author: Edward Haas
Author-email: ehaas@redhat.com
License: LGPL2.1+
Platform: UNKNOWN
License-File: LICENSE
Requires-Dist: PyGObject
Requires-Dist: PyYAML
Requires-Dist: setuptools
Requires-Dist: nispor (>=1.2.1)
